MANIFEST.in
README.md
hack_function.pth
hack_function.py
setup.py
hack_function.egg-info/PKG-INFO
hack_function.egg-info/SOURCES.txt
hack_function.egg-info/dependency_links.txt
hack_function.egg-info/not-zip-safe
hack_function.egg-info/top_level.txt