Metadata-Version: 1.0
Name: hack-function
Version: 1.2.0
Summary: "Goto Definition" for the Python Interpreter.
Home-page: https://github.com/joeyespo/hack-function
Author: Joe Esposito
Author-email: joe@joeyespo.com
License: MIT
Platform: any
